webx/asgi/__init__.py
webx/asgi/core.py
webx/asgi/handler.py
webx/cli/admin.py
webx/cli/monitor.py
webx/config/__init__.py
webx/config/settings.py
webx/core/__init__.py
webx/core/exceptions.py
webx/core/management/boilerplate/__init__.py
webx/core/management/boilerplate/_setup.py
webx/core/management/boilerplate/manage.template
webx/core/management/boilerplate/project/application.template
webx/core/management/boilerplate/project/routes.template
webx/core/management/boilerplate/project/settings.template
webx/core/management/boilerplate/project/views.template
webx/core/management/commands/base.py
webx/core/management/commands/migrate.py
webx/http/__init__.py
webx/http/request.py
webx/http/response.py
webx/httpclient/__init__.py
webx/httpclient/backends/__init__.py
webx/httpclient/backends/async_.py
webx/httpclient/backends/base.py
webx/httpclient/backends/sync.py
webx/monitoring/__init__.py
webx/monitoring/view.py
webx/templating/__init__.py
webx/templating/engine.py
webx/templating/shortcuts.py
webx/tooling/__init__.py
webx/tooling/multidict.py
webx/types/__init__.py
webx/types/asgi.py
webx/views/__init__.py
webx/views/models.py
webx/views/routes.py
webx-0.1.6a0.dist-info/METADATA
webx-0.1.6a0.dist-info/WHEEL
webx-0.1.6a0.dist-info/entry_points.txt
webx-0.1.6a0.dist-info/top_level.txt
webx-0.1.6a0.dist-info/RECORD
