Metadata-Version: 2.1
Name: webx
Version: 0.1.6a0
Summary: A next-generation ASGI Python web-framework, focused on Speed and Stability
Home-page: https://github.com/justanotherbyte/webx
Author: justanotherbyte
License: MIT
Project-URL: Documentation, https://webx.kozumikku.tech/
Project-URL: Issue tracker, https://github.com/justanotherbyte/webx/issues
Platform: UNKNOWN
Classifier: Development Status :: 5 - Production/Stable
Classifier: License :: OSI Approved :: MIT License
Classifier: Intended Audience :: Developers
Classifier: Natural Language :: English
Classifier: Operating System :: OS Independent
Classifier: Programming Language :: Python :: 3.8
Classifier: Programming Language :: Python :: 3.9
Classifier: Topic :: Internet
Classifier: Topic :: Software Development :: Libraries
Classifier: Topic :: Software Development :: Libraries :: Python Modules
Classifier: Topic :: Utilities
Classifier: Typing :: Typed
Requires-Python: >=3.8.0
Requires-Dist: jinja2 (==3.0.3)
Requires-Dist: aiofiles (==0.8.0)
Requires-Dist: click (==8.0.3)
Requires-Dist: rich (==11.0.0)
Requires-Dist: aiosmtplib (==1.1.6)
Requires-Dist: aiohttp (==3.8.1)
Requires-Dist: requests (==2.27.1)
